Workbook

Sheet Sheet2
A3: Row Labels | B3: Sum of unit margin
A4: Gear Assembly 1 (BS4) | B4: 1442
A5: Gear Assembly 2 (BS4) | B5: 3592
A6: Gear Assembly 3 (BS4/6) | B6: 30
A7: Gear Assembly 4 (BS4/6) | B7: 2534
A8: Gear Assembly 5 (BS6) | B8: 3233
A9: Gear Assembly 6 (BS6) | B9: 1029
A10: Grand Total | B10: 11860

Sheet Sheet3
A3: Row Labels | B3: Average of % unit margin
A4: Gear Assembly 1 (BS4) | B4: 12.431034
A5: Gear Assembly 2 (BS4) | B5: 37.084452
A6: Gear Assembly 3 (BS4/6) | B6: 0.22735885
A7: Gear Assembly 4 (BS4/6) | B7: 23.055227
A8: Gear Assembly 5 (BS6) | B8: 33.579144
A9: Gear Assembly 6 (BS6) | B9: 8.2903642
A10: Grand Total | B10: 19.111263

Sheet Sheet4
A3: Row Labels | B3: Sum of Ending Inventory
A4: Q12019-20 | B4: 8616
A5: Q12020-21 | B5: 9311
A6: Q12021-22 | B6: 7466
A7: Q22019-20 | B7: 7681
A8: Q22020-21 | B8: 9278
A9: Q22021-22 | B9: 6601
A10: Q32019-20 | B10: 7826
A11: Q32020-21 | B11: 6375
A12: Q42019-20 | B12: 8751
A13: Q42020-21 | B13: 7901
A14: Grand Total | B14: 79806
B15: =MIN(B4:B13) -> 6375

Sheet Sheet5
A3: Sum of Revenue | B3: Column Labels
A4: Row Labels | B4: 2019-20 | C4: 2020-21 | D4: 2021-22 | E4: Grand Total | H4: Row Labels | I4: 2019-20 | J4: 2020-21 | K4: comparsion
A5: Gear Assembly 1 (BS4) | B5: 29749262 | C5: 28723940 | D5: 12891734 | E5: 71364936 | H5: Gear Assembly 1 (BS4) | I5: 29749262 | J5: 28723940 | K5: =(J5-I5)/I5 -> -0.03446546
A6: Gear Assembly 2 (BS4) | B6: 29682821 | C6: 30472849 | D6: 13838267 | E6: 73993937 | H6: Gear Assembly 2 (BS4) | I6: 29682821 | J6: 30472849 | K6: =(J6-I6)/I6 -> 0.026615664
A7: Gear Assembly 3 (BS4/6) | B7: 26908957 | C7: 32812837 | D7: 12110048 | E7: 71831842 | H7: Gear Assembly 3 (BS4/6) | I7: 26908957 | J7: 32812837 | K7: =(J7-I7)/I7 -> 0.21940204
A8: Gear Assembly 4 (BS4/6) | B8: 31302966 | C8: 30153519 | D8: 13147023 | E8: 74603508 | H8: Gear Assembly 4 (BS4/6) | I8: 31302966 | J8: 30153519 | K8: =(J8-I8)/I8 -> -0.036720067
A9: Gear Assembly 5 (BS6) | B9: 27543062 | C9: 29734073 | D9: 11215976 | E9: 68493111 | H9: Gear Assembly 5 (BS6) | I9: 27543062 | J9: 29734073 | K9: =(J9-I9)/I9 -> 0.079548563
A10: Gear Assembly 6 (BS6) | B10: 29122777 | C10: 30395601 | D10: 14046688 | E10: 73565066 | H10: Gear Assembly 6 (BS6) | I10: 29122777 | J10: 30395601 | K10: =(J10-I10)/I10 -> 0.043705447
A11: Grand Total | B11: 174309845 | C11: 182292819 | D11: 77249736 | E11: 433852400 | J11: max-> | K11: =MAX(K5:K10) -> 0.21940204

Sheet Data
A1: Gear Assembly | B1: GA Category | C1: Month | D1: Quarter | E1: Fiscal Year | F1: Quantity Produced | G1: Sales Quantity | H1: Price | I1: unit overall cost | J1: unit margin | K1: % unit margin | L1: Quarter+year | M1: Ending Inventory | N1: Revenue
A2: Gear Assembly 1 (BS4) | B2: BS4 Only | C2: April | D2: Q1 | E2: 2019-20 | F2: 6336 | G2: 5600 | H2: 432 | I2: =VLOOKUP(A2, Cost!A:I, 9, FALSE) -> 400 | J2: =H2-I2 -> 32 | K2: =(J2/I2)*100 -> 8 | L2: =_xlfn.CONCAT(D2, E2) -> Q12019-20 | M2: =F2 - G2 -> 736 | N2: =G2*H2 -> 2419200
A3: Gear Assembly 1 (BS4) | B3: BS4 Only | C3: May | D3: Q1 | E3: 2019-20 | F3: 5686 | G3: 5523 | H3: 433 | I3: =VLOOKUP(A3, Cost!A:I, 9, FALSE) -> 400 | J3: =H3-I3 -> 33 | K3: =(J3/I3)*100 -> 8.25 | L3: =_xlfn.CONCAT(D3, E3) -> Q12019-20 | M3: =F3 - G3 -> 163 | N3: =G3*H3 -> 2391459
A4: Gear Assembly 1 (BS4) | B4: BS4 Only | C4: June | D4: Q1 | E4: 2019-20 | F4: 6614 | G4: 5726 | H4: 498 | I4: =VLOOKUP(A4, Cost!A:I, 9, FALSE) -> 400 | J4: =H4-I4 -> 98 | K4: =(J4/I4)*100 -> 24.5 | L4: =_xlfn.CONCAT(D4, E4) -> Q12019-20 | M4: =F4 - G4 -> 888 | N4: =G4*H4 -> 2851548
A5: Gear Assembly 1 (BS4) | B5: BS4 Only | C5: July | D5: Q2 | E5: 2019-20 | F5: 5470 | G5: 4916 | H5: 539 | I5: =VLOOKUP(A5, Cost!A:I, 9, FALSE) -> 400 | J5: =H5-I5 -> 139 | K5: =(J5/I5)*100 -> 34.75 | L5: =_xlfn.CONCAT(D5, E5) -> Q22019-20 | M5: =F5 - G5 -> 554 | N5: =G5*H5 -> 2649724
A6: Gear Assembly 1 (BS4) | B6: BS4 Only | C6: August | D6: Q2 | E6: 2019-20 | F6: 6496 | G6: 6089 | H6: 463 | I6: =VLOOKUP(A6, Cost!A:I, 9, FALSE) -> 400 | J6: =H6-I6 -> 63 | K6: =(J6/I6)*100 -> 15.75 | L6: =_xlfn.CONCAT(D6, E6) -> Q22019-20 | M6: =F6 - G6 -> 407 | N6: =G6*H6 -> 2819207
A7: Gear Assembly 1 (BS4) | B7: BS4 Only | C7: September | D7: Q2 | E7: 2019-20 | F7: 5306 | G7: 5032 | H7: 463 | I7: =VLOOKUP(A7, Cost!A:I, 9, FALSE) -> 400 | J7: =H7-I7 -> 63 | K7: =(J7/I7)*100 -> 15.75 | L7: =_xlfn.CONCAT(D7, E7) -> Q22019-20 | M7: =F7 - G7 -> 274 | N7: =G7*H7 -> 2329816
A8: Gear Assembly 1 (BS4) | B8: BS4 Only | C8: October | D8: Q3 | E8: 2019-20 | F8: 5725 | G8: 5478 | H8: 328 | I8: =VLOOKUP(A8, Cost!A:I, 9, FALSE) -> 400 | J8: =H8-I8 -> -72 | K8: =(J8/I8)*100 -> -18 | L8: =_xlfn.CONCAT(D8, E8) -> Q32019-20 | M8: =F8 - G8 -> 247 | N8: =G8*H8 -> 1796784
A9: Gear Assembly 1 (BS4) | B9: BS4 Only | C9: November | D9: Q3 | E9: 2019-20 | F9: 5717 | G9: 5675 | H9: 408 | I9: =VLOOKUP(A9, Cost!A:I, 9, FALSE) -> 400 | J9: =H9-I9 -> 8 | K9: =(J9/I9)*100 -> 2 | L9: =_xlfn.CONCAT(D9, E9) -> Q32019-20 | M9: =F9 - G9 -> 42 | N9: =G9*H9 -> 2315400
A10: Gear Assembly 1 (BS4) | B10: BS4 Only | C10: December | D10: Q3 | E10: 2019-20 | F10: 6043 | G10: 5489 | H10: 341 | I10: =VLOOKUP(A10, Cost!A:I, 9, FALSE) -> 400 | J10: =H10-I10 -> -59 | K10: =(J10/I10)*100 -> -14.75 | L10: =_xlfn.CONCAT(D10, E10) -> Q32019-20 | M10: =F10 - G10 -> 554 | N10: =G10*H10 -> 1871749 | P10: q1 ->
A11: Gear Assembly 1 (BS4) | B11: BS4 Only | C11: January | D11: Q4 | E11: 2019-20 | F11: 6454 | G11: 5869 | H11: 527 | I11: =VLOOKUP(A11, Cost!A:I, 9, FALSE) -> 400 | J11: =H11-I11 -> 127 | K11: =(J11/I11)*100 -> 31.75 | L11: =_xlfn.CONCAT(D11, E11) -> Q42019-20 | M11: =F11 - G11 -> 585 | N11: =G11*H11 -> 3092963 | P11: =_xlfn.MAXIFS(H2:H175, B2:B175, "BS4 Only", D2:D175, "Q1") -> 562
A12: Gear Assembly 1 (BS4) | B12: BS4 Only | C12: February | D12: Q4 | E12: 2019-20 | F12: 6747 | G12: 6019 | H12: 448 | I12: =VLOOKUP(A12, Cost!A:I, 9, FALSE) -> 400 | J12: =H12-I12 -> 48 | K12: =(J12/I12)*100 -> 12 | L12: =_xlfn.CONCAT(D12, E12) -> Q42019-20 | M12: =F12 - G12 -> 728 | N12: =G12*H12 -> 2696512 | P12: =INDEX(A2:A175, MATCH(_xlfn.MAXIFS(H2:H175, B2:B175, "BS4 Only", D2:D175, "Q1"), H2:H175, 0)) -> Gear Assembly 1 (BS4)
A13: Gear Assembly 1 (BS4) | B13: BS4 Only | C13: March | D13: Q4 | E13: 2019-20 | F13: 6690 | G13: 6225 | H13: 404 | I13: =VLOOKUP(A13, Cost!A:I, 9, FALSE) -> 400 | J13: =H13-I13 -> 4 | K13: =(J13/I13)*100 -> 1 | L13: =_xlfn.CONCAT(D13, E13) -> Q42019-20 | M13: =F13 - G13 -> 465 | N13: =G13*H13 -> 2514900
A14: Gear Assembly 1 (BS4) | B14: BS4 Only | C14: April | D14: Q1 | E14: 2020-21 | F14: 5232 | G14: 4858 | H14: 492 | I14: =VLOOKUP(A14, Cost!A:I, 9, FALSE) -> 400 | J14: =H14-I14 -> 92 | K14: =(J14/I14)*100 -> 23 | L14: =_xlfn.CONCAT(D14, E14) -> Q12020-21 | M14: =F14 - G14 -> 374 | N14: =G14*H14 -> 2390136
A15: Gear Assembly 1 (BS4) | B15: BS4 Only | C15: May | D15: Q1 | E15: 2020-21 | F15: 6139 | G15: 5419 | H15: 461 | I15: =VLOOKUP(A15, Cost!A:I, 9, FALSE) -> 400 | J15: =H15-I15 -> 61 | K15: =(J15/I15)*100 -> 15.25 | L15: =_xlfn.CONCAT(D15, E15) -> Q12020-21 | M15: =F15 - G15 -> 720 | N15: =G15*H15 -> 2498159
A16: Gear Assembly 1 (BS4) | B16: BS4 Only | C16: June | D16: Q1 | E16: 2020-21 | F16: 5392 | G16: 4768 | H16: 562 | I16: =VLOOKUP(A16, Cost!A:I, 9, FALSE) -> 400 | J16: =H16-I16 -> 162 | K16: =(J16/I16)*100 -> 40.5 | L16: =_xlfn.CONCAT(D16, E16) -> Q12020-21 | M16: =F16 - G16 -> 624 | N16: =G16*H16 -> 2679616
A17: Gear Assembly 1 (BS4) | B17: BS4 Only | C17: July | D17: Q2 | E17: 2020-21 | F17: 6208 | G17: 5868 | H17: 367 | I17: =VLOOKUP(A17, Cost!A:I, 9, FALSE) -> 400 | J17: =H17-I17 -> -33 | K17: =(J17/I17)*100 -> -8.25 | L17: =_xlfn.CONCAT(D17, E17) -> Q22020-21 | M17: =F17 - G17 -> 340 | N17: =G17*H17 -> 2153556
A18: Gear Assembly 1 (BS4) | B18: BS4 Only | C18: August | D18: Q2 | E18: 2020-21 | F18: 6567 | G18: 5966 | H18: 341 | I18: =VLOOKUP(A18, Cost!A:I, 9, FALSE) -> 400 | J18: =H18-I18 -> -59 | K18: =(J18/I18)*100 -> -14.75 | L18: =_xlfn.CONCAT(D18, E18) -> Q22020-21 | M18: =F18 - G18 -> 601 | N18: =G18*H18 -> 2034406
A19: Gear Assembly 1 (BS4) | B19: BS4 Only | C19: September | D19: Q2 | E19: 2020-21 | F19: 6063 | G19: 5849 | H19: 525 | I19: =VLOOKUP(A19, Cost!A:I, 9, FALSE) -> 400 | J19: =H19-I19 -> 125 | K19: =(J19/I19)*100 -> 31.25 | L19: =_xlfn.CONCAT(D19, E19) -> Q22020-21 | M19: =F19 - G19 -> 214 | N19: =G19*H19 -> 3070725
A20: Gear Assembly 1 (BS4) | B20: BS4 Only | C20: October | D20: Q3 | E20: 2020-21 | F20: 6311 | G20: 6254 | H20: 419 | I20: =VLOOKUP(A20, Cost!A:I, 9, FALSE) -> 400 | J20: =H20-I20 -> 19 | K20: =(J20/I20)*100 -> 4.75 | L20: =_xlfn.CONCAT(D20, E20) -> Q32020-21 | M20: =F20 - G20 -> 57 | N20: =G20*H20 -> 2620426
A21: Gear Assembly 1 (BS4) | B21: BS4 Only | C21: November | D21: Q3 | E21: 2020-21 | F21: 5220 | G21: 5082 | H21: 524 | I21: =VLOOKUP(A21, Cost!A:I, 9, FALSE) -> 400 | J21: =H21-I21 -> 124 | K21: =(J21/I21)*100 -> 31 | L21: =_xlfn.CONCAT(D21, E21) -> Q32020-21 | M21: =F21 - G21 -> 138 | N21: =G21*H21 -> 2662968
A22: Gear Assembly 1 (BS4) | B22: BS4 Only | C22: December | D22: Q3 | E22: 2020-21 | F22: 5626 | G22: 5190 | H22: 461 | I22: =VLOOKUP(A22, Cost!A:I, 9, FALSE) -> 400 | J22: =H22-I22 -> 61 | K22: =(J22/I22)*100 -> 15.25 | L22: =_xlfn.CONCAT(D22, E22) -> Q32020-21 | M22: =F22 - G22 -> 436 | N22: =G22*H22 -> 2392590
A23: Gear Assembly 1 (BS4) | B23: BS4 Only | C23: January | D23: Q4 | E23: 2020-21 | F23: 5832 | G23: 5270 | H23: 381 | I23: =VLOOKUP(A23, Cost!A:I, 9, FALSE) -> 400 | J23: =H23-I23 -> -19 | K23: =(J23/I23)*100 -> -4.75 | L23: =_xlfn.CONCAT(D23, E23) -> Q42020-21 | M23: =F23 - G23 -> 562 | N23: =G23*H23 -> 2007870
A24: Gear Assembly 1 (BS4) | B24: BS4 Only | C24: February | D24: Q4 | E24: 2020-21 | F24: 5592 | G24: 5241 | H24: 424 | I24: =VLOOKUP(A24, Cost!A:I, 9, FALSE) -> 400 | J24: =H24-I24 -> 24 | K24: =(J24/I24)*100 -> 6 | L24: =_xlfn.CONCAT(D24, E24) -> Q42020-21 | M24: =F24 - G24 -> 351 | N24: =G24*H24 -> 2222184
... A175: Gear Assembly 6 (BS6) | B175: BS6 Only | C175: August | D175: Q2 | E175: 2021-22 | F175: 6145 | G175: 5647 | H175: 489 | I175: =VLOOKUP(A175, Cost!A:I, 9, FALSE) -> 428 | J175: =H175-I175 -> 61 | K175: =(J175/I175)*100 -> 14.252336 | L175: =_xlfn.CONCAT(D175, E175) -> Q22021-22 | M175: =F175 - G175 -> 498 | N175: =G175*H175 -> 2761383

Sheet Cost
A1: SALES DETAILS (GEAR ASSEMBLIES) | B1: FY | C1: CC | D1: Direct Materials | E1: Direct Labour | F1: Production Overhead | G1: G&A Overhead | H1: Finance Costs | I1: Unit Overall Product Cost
A2: Gear Assembly 1 (BS4) | B2: 2019-20 | C2: =CONCATENATE(A2,B2) -> Gear Assembly 1 (BS4)2019-20 | D2: 165 | E2: 48 | F2: 108 | G2: 48 | H2: 31 | I2: =D2+E2+F2+G2+H2 -> 400
A3: Gear Assembly 2 (BS4) | B3: 2019-20 | C3: =CONCATENATE(A3,B3) -> Gear Assembly 2 (BS4)2019-20 | D3: 132 | E3: 51 | F3: 75 | G3: 49 | H3: 27 | I3: =D3+E3+F3+G3+H3 -> 334
A4: Gear Assembly 3 (BS4/6) | B4: 2019-20 | C4: =CONCATENATE(A4,B4) -> Gear Assembly 3 (BS4/6)2019-20 | D4: 189 | E4: 65 | F4: 120 | G4: 49 | H4: 32 | I4: =D4+E4+F4+G4+H4 -> 455
A5: Gear Assembly 4 (BS4/6) | B5: 2019-20 | C5: =CONCATENATE(A5,B5) -> Gear Assembly 4 (BS4/6)2019-20 | D5: 141 | E5: 49 | F5: 112 | G5: 45 | H5: 32 | I5: =D5+E5+F5+G5+H5 -> 379
A6: Gear Assembly 5 (BS6) | B6: 2019-20 | C6: =CONCATENATE(A6,B6) -> Gear Assembly 5 (BS6)2019-20 | D6: 139 | E6: 51 | F6: 70 | G6: 46 | H6: 26 | I6: =D6+E6+F6+G6+H6 -> 332
A7: Gear Assembly 6 (BS6) | B7: 2019-20 | C7: =CONCATENATE(A7,B7) -> Gear Assembly 6 (BS6)2019-20 | D7: 171 | E7: 69 | F7: 109 | G7: 46 | H7: 33 | I7: =D7+E7+F7+G7+H7 -> 428
A8: Gear Assembly 1 (BS4) | B8: 2020-21 | C8: =CONCATENATE(A8,B8) -> Gear Assembly 1 (BS4)2020-21 | D8: 209 | E8: 52 | F8: 114 | G8: 47 | H8: 30 | I8: =D8+E8+F8+G8+H8 -> 452
A9: Gear Assembly 2 (BS4) | B9: 2020-21 | C9: =CONCATENATE(A9,B9) -> Gear Assembly 2 (BS4)2020-21 | D9: 178 | E9: 56 | F9: 79 | G9: 46 | H9: 26 | I9: =D9+E9+F9+G9+H9 -> 385
A10: Gear Assembly 3 (BS4/6) | B10: 2020-21 | C10: =CONCATENATE(A10,B10) -> Gear Assembly 3 (BS4/6)2020-21 | D10: 229 | E10: 78 | F10: 126 | G10: 46 | H10: 31 | I10: =D10+E10+F10+G10+H10 -> 510
A11: Gear Assembly 4 (BS4/6) | B11: 2020-21 | C11: =CONCATENATE(A11,B11) -> Gear Assembly 4 (BS4/6)2020-21 | D11: 171 | E11: 53 | F11: 106 | G11: 48 | H11: 30 | I11: =D11+E11+F11+G11+H11 -> 408
A12: Gear Assembly 5 (BS6) | B12: 2020-21 | C12: =CONCATENATE(A12,B12) -> Gear Assembly 5 (BS6)2020-21 | D12: 171 | E12: 57 | F12: 66 | G12: 47 | H12: 26 | I12: =D12+E12+F12+G12+H12 -> 367
A13: Gear Assembly 6 (BS6) | B13: 2020-21 | C13: =CONCATENATE(A13,B13) -> Gear Assembly 6 (BS6)2020-21 | D13: 204 | E13: 74 | F13: 108 | G13: 45 | H13: 31 | I13: =D13+E13+F13+G13+H13 -> 462
... A19: Gear Assembly 6 (BS6) | B19: 2021-22 | C19: =CONCATENATE(A19,B19) -> Gear Assembly 6 (BS6)2021-22 | D19: 208 | E19: 77 | F19: 138 | G19: 54 | H19: 35 | I19: =D19+E19+F19+G19+H19 -> 512

Sheet Shift_Running
A1: Date | B1: Shift 1 (8 Hours) | C1: Shift 2 (8 Hours) | D1: Shift 3 (8 Hours)
A2: 44652 | B2: Operational | C2: Operational | D2: Operational
A3: 44653 | B3: Operational | C3: Operational | D3: Operational
A4: 44654 | B4: Operational | C4: Operational | D4: Operational
A5: 44655 | B5: Operational | C5: Operational | D5: Operational
A6: 44656 | B6: Breakdown | C6: Operational | D6: Operational
A7: 44657 | B7: Operational | C7: Operational | D7: Planned Maintenance
A8: 44658 | B8: Operational | C8: Operational | D8: Operational
A9: 44659 | B9: Operational | C9: Operational | D9: Operational
A10: 44660 | B10: Operational | C10: Unplanned Maintenance | D10: Operational
A11: 44661 | B11: Operational | C11: Operational | D11: Operational
A12: 44662 | B12: Operational | C12: Operational | D12: Operational
A13: 44663 | B13: Operational | C13: Operational | D13: Operational
... A15: 44665 | B15: Power Cut | C15: Power Cut | D15: Power Cut

Sheet Actual_Output
A1: Date | B1: Shift 1 | C1: Shift 2 | D1: Shift 3 | E1: total_prod
A2: 44652 | B2: 3973 | C2: 4035 | D2: 4200 | E2: =B2+C2+D2 -> 12208
A3: 44653 | B3: 3922 | C3: 3981 | D3: 4175 | E3: =B3+C3+D3 -> 12078
A4: 44654 | B4: 4043 | C4: 4200 | D4: 4189 | E4: =B4+C4+D4 -> 12432
A5: 44655 | B5: 4022 | C5: 4090 | D5: 4361 | E5: =B5+C5+D5 -> 12473
A6: 44656 | B6: 0 | C6: 4143 | D6: 4536 | E6: =B6+C6+D6 -> 8679
A7: 44657 | B7: 4400 | C7: 4280 | D7: 0 | E7: =B7+C7+D7 -> 8680
A8: 44658 | B8: 4346 | C8: 4033 | D8: 4464 | E8: =B8+C8+D8 -> 12843
A9: 44659 | B9: 3882 | C9: 4274 | D9: 4448 | E9: =B9+C9+D9 -> 12604
A10: 44660 | B10: 4336 | C10: 0 | D10: 4540 | E10: =B10+C10+D10 -> 8876
A11: 44661 | B11: 4069 | C11: 4038 | D11: 4033 | E11: =B11+C11+D11 -> 12140
A12: 44662 | B12: 4194 | C12: 4066 | D12: 4577 | E12: =B12+C12+D12 -> 12837
A13: 44663 | B13: 4360 | C13: 4272 | D13: 4169 | E13: =B13+C13+D13 -> 12801
... A15: 44665 | B15: 0 | C15: 0 | D15: 0 | E15: =B15+C15+D15 -> 0
D16: sum -> | E16: =SUM(E2:E15) -> 151052

Sheet Scrap
A1: Date | B1: Shift 1 | C1: Shift 2 | D1: Shift 3 | E1: scrap_total
A2: 44652 | B2: 16 | C2: 27 | D2: 20 | E2: =B2+C2+D2 -> 63
A3: 44653 | B3: 24 | C3: 21 | D3: 42 | E3: =B3+C3+D3 -> 87
A4: 44654 | B4: 6 | C4: 21 | D4: 1 | E4: =B4+C4+D4 -> 28
A5: 44655 | B5: 23 | C5: 33 | D5: 7 | E5: =B5+C5+D5 -> 63
A6: 44656 | B6: 0 | C6: 25 | D6: 13 | E6: =B6+C6+D6 -> 38
A7: 44657 | B7: 21 | C7: 21 | D7: 0 | E7: =B7+C7+D7 -> 42
A8: 44658 | B8: 18 | C8: 25 | D8: 32 | E8: =B8+C8+D8 -> 75
A9: 44659 | B9: 5 | C9: 23 | D9: 50 | E9: =B9+C9+D9 -> 78
A10: 44660 | B10: 9 | C10: 0 | D10: 38 | E10: =B10+C10+D10 -> 47
A11: 44661 | B11: 4 | C11: 34 | D11: 26 | E11: =B11+C11+D11 -> 64
A12: 44662 | B12: 16 | C12: 21 | D12: 27 | E12: =B12+C12+D12 -> 64
A13: 44663 | B13: 20 | C13: 35 | D13: 48 | E13: =B13+C13+D13 -> 103
... A15: 44665 | B15: 0 | C15: 0 | D15: 0 | E15: =B15+C15+D15 -> 0
D16: sum -> | E16: =SUM(E2:E15) -> 817
